galangal/__init__.py
galangal/__main__.py
galangal/cli.py
galangal/exceptions.py
galangal/logging.py
galangal/mistakes.py
galangal/py.typed
galangal/results.py
galangal/ai/__init__.py
galangal/ai/base.py
galangal/ai/claude.py
galangal/ai/codex.py
galangal/ai/errors.py
galangal/ai/gemini.py
galangal/ai/subprocess.py
galangal/commands/__init__.py
galangal/commands/archive.py
galangal/commands/complete.py
galangal/commands/config.py
galangal/commands/doctor.py
galangal/commands/github.py
galangal/commands/hub.py
galangal/commands/init.py
galangal/commands/init_wizard.py
galangal/commands/list.py
galangal/commands/mistakes.py
galangal/commands/pause.py
galangal/commands/prompts.py
galangal/commands/reset.py
galangal/commands/resume.py
galangal/commands/skip.py
galangal/commands/start.py
galangal/commands/status.py
galangal/commands/switch.py
galangal/config/__init__.py
galangal/config/defaults.py
galangal/config/loader.py
galangal/config/schema.py
galangal/core/__init__.py
galangal/core/artifacts.py
galangal/core/git_utils.py
galangal/core/lineage.py
galangal/core/state.py
galangal/core/tasks.py
galangal/core/utils.py
galangal/core/version_check.py
galangal/core/workflow/__init__.py
galangal/core/workflow/core.py
galangal/core/workflow/engine.py
galangal/core/workflow/pause.py
galangal/core/workflow/tui_runner.py
galangal/github/__init__.py
galangal/github/client.py
galangal/github/images.py
galangal/github/issues.py
galangal/hub/__init__.py
galangal/hub/action_handler.py
galangal/hub/client.py
galangal/hub/config.py
galangal/hub/hooks.py
galangal/prompts/__init__.py
galangal/prompts/builder.py
galangal/prompts/defaults/benchmark.md
galangal/prompts/defaults/contract.md
galangal/prompts/defaults/design.md
galangal/prompts/defaults/dev.md
galangal/prompts/defaults/docs.md
galangal/prompts/defaults/migration.md
galangal/prompts/defaults/pm.md
galangal/prompts/defaults/pm_questions.md
galangal/prompts/defaults/preflight.md
galangal/prompts/defaults/qa.md
galangal_orchestrate-0.29.7.dist-info/METADATA
galangal_orchestrate-0.29.7.dist-info/WHEEL
galangal_orchestrate-0.29.7.dist-info/entry_points.txt
galangal_orchestrate-0.29.7.dist-info/licenses/LICENSE
galangal_orchestrate-0.29.7.dist-info/RECORD
