Metadata-Version: 2.4
Name: galangal-orchestrate
Version: 0.29.7
Summary: AI-driven development workflow orchestrator
Project-URL: Homepage, https://github.com/Galangal-Media/galangal-orchestrate
Project-URL: Repository, https://github.com/Galangal-Media/galangal-orchestrate
Project-URL: Issues, https://github.com/Galangal-Media/galangal-orchestrate/issues
Author: Galangal Media
License-Expression: MIT
License-File: LICENSE
Keywords: ai,claude,development,orchestrator,workflow
Classifier: Development Status :: 4 - Beta
Classifier: Environment :: Console
Classifier: Intended Audience :: Developers
Classifier: License :: OSI Approved :: MIT License
Classifier: Operating System :: OS Independent
Classifier: Programming Language :: Python :: 3
Classifier: Programming Language :: Python :: 3.10
Classifier: Programming Language :: Python :: 3.11
Classifier: Programming Language :: Python :: 3.12
Classifier: Programming Language :: Python :: 3.13
Classifier: Topic :: Software Development
Classifier: Topic :: Software Development :: Quality Assurance
Requires-Python: >=3.10
Requires-Dist: pydantic>=2.0.0
Requires-Dist: pyyaml>=6.0
Requires-Dist: rich>=13.0.0
Requires-Dist: sentence-transformers>=2.2.0
Requires-Dist: sqlite-vss>=0.1.2
Requires-Dist: structlog>=24.0.0
Requires-Dist: textual>=0.40.0
Requires-Dist: websockets>=12.0
Provides-Extra: dev
Requires-Dist: mypy>=1.0.0; extra == 'dev'
Requires-Dist: pytest-asyncio>=0.21.0; extra == 'dev'
Requires-Dist: pytest-cov>=4.0.0; extra == 'dev'
Requires-Dist: pytest>=7.0.0; extra == 'dev'
Requires-Dist: ruff>=0.1.0; extra == 'dev'
Provides-Extra: hub
Requires-Dist: aiosqlite>=0.19.0; extra == 'hub'
Requires-Dist: fastapi>=0.109.0; extra == 'hub'
Requires-Dist: jinja2>=3.1.0; extra == 'hub'
Requires-Dist: python-multipart>=0.0.6; extra == 'hub'
Requires-Dist: uvicorn>=0.27.0; extra == 'hub'
Requires-Dist: websockets>=12.0; extra == 'hub'
